how_to_opensource/__init__.py
how_to_opensource/_version.py
how_to_opensource/core.py
QM_How_to_Opensource_Louis-0.0.2.dist-info/METADATA
QM_How_to_Opensource_Louis-0.0.2.dist-info/WHEEL
QM_How_to_Opensource_Louis-0.0.2.dist-info/top_level.txt
QM_How_to_Opensource_Louis-0.0.2.dist-info/RECORD
