Metadata-Version: 2.1
Name: QM-How-to-Opensource-Louis
Version: 0.0.2
Summary: A Quantmetry tutorial on how to publish an opensource python package.
Home-page: http://packages.python.org/how_to_opensource
Author: Louis Lacombe
Author-email: lfmm.lacombe@gmail.com
License: BSD
Keywords: example opensource tutorial
Platform: UNKNOWN
Classifier: License :: OSI Approved :: BSD License
Classifier: Programming Language :: Python :: 3.9
Requires-Dist: numpy (>=1.20)
Provides-Extra: docs
Requires-Dist: sphinx ; extra == 'docs'
Requires-Dist: sphinx-gallery ; extra == 'docs'
Requires-Dist: sphinx-rtd-theme ; extra == 'docs'
Requires-Dist: numpydoc ; extra == 'docs'
Provides-Extra: tests
Requires-Dist: flake8 ; extra == 'tests'
Requires-Dist: mypy ; extra == 'tests'
Requires-Dist: pytest-cov ; extra == 'tests'
